Workbook

Sheet Cronograma
B2: Maria Isabel
B3: Adriana | T3: 6
B4: Airbnb
B5: Booking
B6: Cortesías
B7: No autorizado
B9: 2024 | I9: 2025 | P9: 2026
B10: LUNES | C10: MARTES | D10: MIÉRCOLES | E10: JUEVES | F10: VIERNES | G10: SÁBADO | H10: DOMINGO | I10: LUNES | J10: MARTES | K10: MIÉRCOLES | L10: JUEVES | M10: VIERNES | N10: SÁBADO | O10: DOMINGO | P10: LUNES | Q10: MARTES | R10: MIÉRCOLES | S10: JUEVES | T10: VIERNES | U10: SÁBADO | V10: DOMINGO
B11: ENERO | I11: ENERO | P11: ENERO
B12: 1 | C12: 2 | D12: 3 | E12: 4 | F12: 5 | G12: 6 | H12: 7 | I12: 30 | J12: 31 | K12: 1 | L12: 2 | M12: 3 | N12: 4 | O12: 5 | P12: 29 | Q12: 30 | R12: 31 | S12: 1 | T12: 2 | U12: 3 | V12: 4
J13: Diego Quintero | N13: Claudia Cifuentes | P13: Maritza Mosquera Airbnb | U13: Nicolay Gil Airbnb
B14: 8 | C14: 9 | D14: 10 | E14: 11 | F14: 12 | G14: 13 | H14: 14 | I14: 6 | J14: 7 | K14: 8 | L14: 9 | M14: 10 | N14: 11 | O14: 12 | P14: 5 | Q14: 6 | R14: 7 | S14: 8 | T14: 9 | U14: 10 | V14: 11
I15: Claudia Cifuentes | N15: Marly Andrea Díaz | Q15: Santiago Benavides
B16: 15 | C16: 16 | D16: 17 | E16: 18 | F16: 19 | G16: 20 | H16: 21 | I16: 13 | J16: 14 | K16: 15 | L16: 16 | M16: 17 | N16: 18 | O16: 19 | P16: 12 | Q16: 13 | R16: 14 | S16: 15 | T16: 16 | U16: 17 | V16: 18
J17: COR Alejandra Agudelo | N17: Catherine Tabares Airbnb | P17: Santiago | U17: Andrés Santiago Airbnb
B18: 22 | C18: 23 | D18: 24 | E18: 25 | F18: 26 | G18: 27 | H18: 28 | I18: 20 | J18: 21 | K18: 22 | L18: 23 | M18: 24 | N18: 25 | O18: 26 | P18: 19 | Q18: 20 | R18: 21 | S18: 22 | T18: 23 | U18: 24 | V18: 25
N19: Hernando Díaz Airbnb | P19: COR Alejandra Agudelo | U19: Yaneth Rodríguez
B20: 29 | C20: 30 | D20: 31 | E20: 1 | F20: 2 | G20: 3 | H20: 4 | I20: 27 | J20: 28 | K20: 29 | L20: 30 | M20: 31 | N20: 1 | O20: 2 | P20: 26 | Q20: 27 | R20: 28 | S20: 29 | T20: 30 | U20: 31 | V20: 1
N21: Julián Betancourth | U21: Natalia Acevedo
B22: FEBRERO | I22: FEBRERO | P22: FEBRERO
B23: 5 | C23: 6 | D23: 7 | E23: 8 | F23: 9 | G23: 10 | H23: 11 | I23: 3 | J23: 4 | K23: 5 | L23: 6 | M23: 7 | N23: 8 | O23: 9 | P23: 2 | Q23: 3 | R23: 4 | S23: 5 | T23: 6 | U23: 7 | V23: 8
N24: Valentina Tabares Airbnb | U24: Luceyda Londoño
B25: 12 | C25: 13 | D25: 14 | E25: 15 | F25: 16 | G25: 17 | H25: 18 | I25: 10 | J25: 11 | K25: 12 | L25: 13 | M25: 14 | N25: 15 | O25: 16 | P25: 9 | Q25: 10 | R25: 11 | S25: 12 | T25: 13 | U25: 14 | V25: 15
N26: Angela Sierra | U26: Andrea Grisales Airbnb
B27: 19 | C27: 20 | D27: 21 | E27: 22 | F27: 23 | G27: 24 | H27: 25 | I27: 17 | J27: 18 | K27: 19 | L27: 20 | M27: 21 | N27: 22 | O27: 23 | P27: 16 | Q27: 17 | R27: 18 | S27: 19 | T27: 20 | U27: 21 | V27: 22
N28: Maria Camila Airbnb | S28: Walther Ivan Sanchez Airbnb | V28: William Brion
B29: 26 | C29: 27 | D29: 28 | E29: 29 | F29: 1 | G29: 2 | H29: 3 | I29: 24 | J29: 25 | K29: 26 | L29: 27 | M29: 28 | N29: 1 | O29: 2 | P29: 23 | Q29: 24 | R29: 25 | S29: 26 | T29: 27 | U29: 28 | V29: 1
N30: Paola Laguna | U30: Paula Andrea Ríos
B31: MARZO | I31: MARZO | P31: MARZO
B32: 4 | C32: 5 | D32: 6 | E32: 7 | F32: 8 | G32: 9 | H32: 10 | I32: 3 | J32: 4 | K32: 5 | L32: 6 | M32: 7 | N32: 8 | O32: 9 | P32: 2 | Q32: 3 | R32: 4 | S32: 5 | T32: 6 | U32: 7 | V32: 8
U33: Julián David Muñoz Airbnb
B34: 11 | C34: 12 | D34: 13 | E34: 14 | F34: 15 | G34: 16 | H34: 17 | I34: 10 | J34: 11 | K34: 12 | L34: 13 | M34: 14 | N34: 15 | O34: 16 | P34: 9 | Q34: 10 | R34: 11 | S34: 12 | T34: 13 | U34: 14 | V34: 15
N35: Adolfo Bermudez
B36: 18 | C36: 19 | D36: 20 | E36: 21 | F36: 22 | G36: 23 | H36: 24 | I36: 17 | J36: 18 | K36: 19 | L36: 20 | M36: 21 | N36: 22 | O36: 23 | P36: 16 | Q36: 17 | R36: 18 | S36: 19 | T36: 20 | U36: 21 | V36: 22
N37: Stephanie Gasca Airbnb | U37: Luceyda Londoño
B38: 25 | C38: 26 | D38: 27 | E38: 28 | F38: 29 | G38: 30 | H38: 31 | I38: 24 | J38: 25 | K38: 26 | L38: 27 | M38: 28 | N38: 29 | O38: 30 | P38: 23 | Q38: 24 | R38: 25 | S38: 26 | T38: 27 | U38: 28 | V38: 29
I39: Stephanie Airbnb | N39: Camilo Lucero Airbnb | P39: Santiago
B40: ABRIL | I40: ABRIL | P40: ABRIL
B41: 1 | C41: 2 | D41: 3 | E41: 4 | F41: 5 | G41: 6 | H41: 7 | I41: 31 | J41: 1 | K41: 2 | L41: 3 | M41: 4 | N41: 5 | O41: 6 | P41: 30 | Q41: 31 | R41: 1 | S41: 2 | T41: 3 | U41: 4 | V41: 5
B43: 8 | C43: 9 | D43: 10 | E43: 11 | F43: 12 | G43: 13 | H43: 14 | I43: 7 | J43: 8 | K43: 9 | L43: 10 | M43: 11 | N43: 12 | O43: 13 | P43: 6 | Q43: 7 | R43: 8 | S43: 9 | T43: 10 | U43: 11 | V43: 12
U44: Daniela
B45: 15 | C45: 16 | D45: 17 | E45: 18 | F45: 19 | G45: 20 | H45: 21 | I45: 14 | J45: 15 | K45: 16 | L45: 17 | M45: 18 | N45: 19 | O45: 20 | P45: 13 | Q45: 14 | R45: 15 | S45: 16 | T45: 17 | U45: 18 | V45: 19
L46: Jhon Zabala Airbnb
B47: 22 | C47: 23 | D47: 24 | E47: 25 | F47: 26 | G47: 27 | H47: 28 | I47: 21 | J47: 22 | K47: 23 | L47: 24 | M47: 25 | N47: 26 | O47: 27 | P47: 20 | Q47: 21 | R47: 22 | S47: 23 | T47: 24 | U47: 25 | V47: 26
I48: Jaime Soto
B49: MAYO | I49: MAYO | P49: MAYO
B50: 29 | C50: 30 | D50: 1 | E50: 2 | F50: 3 | G50: 4 | H50: 5 | I50: 28 | J50: 29 | K50: 30 | L50: 1 | M50: 2 | N50: 3 | O50: 4 | P50: 27 | Q50: 28 | R50: 29 | S50: 30 | T50: 1 | U50: 2 | V50: 3
K51: Erika Airbnb | N51: Mayerlin Airbnb
B52: 6 | C52: 7 | D52: 8 | E52: 9 | F52: 10 | G52: 11 | H52: 12 | I52: 5 | J52: 6 | K52: 7 | L52: 8 | M52: 9 | N52: 10 | O52: 11 | P52: 4 | Q52: 5 | R52: 6 | S52: 7 | T52: 8 | U52: 9 | V52: 10
N53: Richard Airbnb
B54: 13 | C54: 14 | D54: 15 | E54: 16 | F54: 17 | G54: 18 | H54: 19 | I54: 12 | J54: 13 | K54: 14 | L54: 15 | M54: 16 | N54: 17 | O54: 18 | P54: 11 | Q54: 12 | R54: 13 | S54: 14 | T54: 15 | U54: 16 | V54: 17
M55: Santiago Benavides Airbnb
B56: 20 | C56: 21 | D56: 22 | E56: 23 | F56: 24 | G56: 25 | H56: 26 | I56: 19 | J56: 20 | K56: 21 | L56: 22 | M56: 23 | N56: 24 | O56: 25 | P56: 18 | Q56: 19 | R56: 20 | S56: 21 | T56: 22 | U56: 23 | V56: 24
I57: Airbnb | N57: Natalia Acevedo
B58: 27 | C58: 28 | D58: 29 | E58: 30 | F58: 31 | G58: 1 | H58: 2 | I58: 26 | J58: 27 | K58: 28 | L58: 29 | M58: 30 | N58: 31 | O58: 1 | P58: 25 | Q58: 26 | R58: 27 | S58: 28 | T58: 29 | U58: 30 | V58: 31
N59: Camilo Airbnb
B60: JUNIO | I60: JUNIO | P60: JUNIO
B61: 3 | C61: 4 | D61: 5 | E61: 6 | F61: 7 | G61: 8 | H61: 9 | I61: 2 | J61: 3 | K61: 4 | L61: 5 | M61: 6 | N61: 7 | O61: 8 | P61: 1 | Q61: 2 | R61: 3 | S61: 4 | T61: 5 | U61: 6 | V61: 7
N62: Adriana Herrera Booking
B63: 10 | C63: 11 | D63: 12 | E63: 13 | F63: 14 | G63: 15 | H63: 16 | I63: 9 | J63: 10 | K63: 11 | L63: 12 | M63: 13 | N63: 14 | O63: 15 | P63: 8 | Q63: 9 | R63: 10 | S63: 11 | T63: 12 | U63: 13 | V63: 14
L64: Juan David Vidal
B65: 17 | C65: 18 | D65: 19 | E65: 20 | F65: 21 | G65: 22 | H65: 23 | I65: 16 | J65: 17 | K65: 18 | L65: 19 | M65: 20 | N65: 21 | O65: 22 | P65: 15 | Q65: 16 | R65: 17 | S65: 18 | T65: 19 | U65: 20 | V65: 21
N66: Maricela
B67: 24 | C67: 25 | D67: 26 | E67: 27 | F67: 28 | G67: 29 | H67: 30 | I67: 23 | J67: 24 | K67: 25 | L67: 26 | M67: 27 | N67: 28 | O67: 29 | P67: 22 | Q67: 23 | R67: 24 | S67: 25 | T67: 26 | U67: 27 | V67: 28
I68: Maricela | M68: Alejandra Rivera Booking
B69: JULIO | I69: JULIO | P69: JULIO
B70: 1 | C70: 2 | D70: 3 | E70: 4 | F70: 5 | G70: 6 | H70: 7 | I70: 30 | J70: 1 | K70: 2 | L70: 3 | M70: 4 | N70: 5 | O70: 6 | P70: 29 | Q70: 30 | R70: 1 | S70: 2 | T70: 3 | U70: 4 | V70: 5
I71: Booking | J71: Alejandra Agudelo N/A | N71: Lorena Airbnb
B72: 8 | C72: 9 | D72: 10 | E72: 11 | F72: 12 | G72: 13 | H72: 14 | I72: 7 | J72: 8 | K72: 9 | L72: 10 | M72: 11 | N72: 12 | O72: 13 | P72: 6 | Q72: 7 | R72: 8 | S72: 9 | T72: 10 | U72: 11 | V72: 12
N73: Mario Airbnb
B74: 15 | C74: 16 | D74: 17 | E74: 18 | F74: 19 | G74: 20 | H74: 21 | I74: 14 | J74: 15 | K74: 16 | L74: 17 | M74: 18 | N74: 19 | O74: 20 | P74: 13 | Q74: 14 | R74: 15 | S74: 16 | T74: 17 | U74: 18 | V74: 19
N75: Victor Manuel
B76: 22 | C76: 23 | D76: 24 | E76: 25 | F76: 26 | G76: 27 | H76: 28 | I76: 21 | J76: 22 | K76: 23 | L76: 24 | M76: 25 | N76: 26 | O76: 27 | P76: 20 | Q76: 21 | R76: 22 | S76: 23 | T76: 24 | U76: 25 | V76: 26
J77: Alejandra Agudelo N/A | N77: Yubis Saavedra
B78: 29 | C78: 30 | D78: 31 | E78: 1 | F78: 2 | G78: 3 | H78: 4 | I78: 28 | J78: 29 | K78: 30 | L78: 31 | M78: 1 | N78: 2 | O78: 3 | P78: 27 | Q78: 28 | R78: 29 | S78: 30 | T78: 31 | U78: 1 | V78: 2
N79: Valentina Hidalgo Airbnb
B80: AGOSTO | I80: AGOSTO | P80: AGOSTO
B81: 5 | C81: 6 | D81: 7 | E81: 8 | F81: 9 | G81: 10 | H81: 11 | I81: 4 | J81: 5 | K81: 6 | L81: 7 | M81: 8 | N81: 9 | O81: 10 | P81: 3 | Q81: 4 | R81: 5 | S81: 6 | T81: 7 | U81: 8 | V81: 9
I82: Jose Rey Airbnb | L82: Juan David Vidal | N82: Tatiana Gallego
B83: 12 | C83: 13 | D83: 14 | E83: 15 | F83: 16 | G83: 17 | H83: 18 | I83: 11 | J83: 12 | K83: 13 | L83: 14 | M83: 15 | N83: 16 | O83: 17 | P83: 10 | Q83: 11 | R83: 12 | S83: 13 | T83: 14 | U83: 15 | V83: 16
N84: Jonathan Harf Airbnb
B85: 19 | C85: 20 | D85: 21 | E85: 22 | F85: 23 | G85: 24 | H85: 25 | I85: 18 | J85: 19 | K85: 20 | L85: 21 | M85: 22 | N85: 23 | O85: 24 | P85: 17 | Q85: 18 | R85: 19 | S85: 20 | T85: 21 | U85: 22 | V85: 23
I86: Airbnb | N86: Paola Laguna
B87: 26 | C87: 27 | D87: 28 | E87: 29 | F87: 30 | G87: 31 | H87: 1 | I87: 25 | J87: 26 | K87: 27 | L87: 28 | M87: 29 | N87: 30 | O87: 31 | P87: 24 | Q87: 25 | R87: 26 | S87: 27 | T87: 28 | U87: 29 | V87: 30
N88: Daniela Gónzalez
B89: SEPTIEMBRE | I89: SEPTIEMBRE | P89: SEPTIEMBRE
B90: 2 | C90: 3 | D90: 4 | E90: 5 | F90: 6 | G90: 7 | H90: 8 | I90: 1 | J90: 2 | K90: 3 | L90: 4 | M90: 5 | N90: 6 | O90: 7 | P90: 31 | Q90: 1 | R90: 2 | S90: 3 | T90: 4 | U90: 5 | V90: 6
N91: Daniela Quintero
B92: 9 | C92: 10 | D92: 11 | E92: 12 | F92: 13 | G92: 14 | H92: 15 | I92: 8 | J92: 9 | K92: 10 | L92: 11 | M92: 12 | N92: 13 | O92: 14 | P92: 7 | Q92: 8 | R92: 9 | S92: 10 | T92: 11 | U92: 12 | V92: 13
G93: Viviana Martínez | N93: Tatiana Rodríguez
B94: 16 | C94: 17 | D94: 18 | E94: 19 | F94: 20 | G94: 21 | H94: 22 | I94: 15 | J94: 16 | K94: 17 | L94: 18 | M94: 19 | N94: 20 | O94: 21 | P94: 14 | Q94: 15 | R94: 16 | S94: 17 | T94: 18 | U94: 19 | V94: 20
G95: Alejandra Linares / Erly Aragon | N95: Alberto Trujillo Airbnb
B96: 23 | C96: 24 | D96: 25 | E96: 26 | F96: 27 | G96: 28 | H96: 29 | I96: 22 | J96: 23 | K96: 24 | L96: 25 | M96: 26 | N96: 27 | O96: 28 | P96: 21 | Q96: 22 | R96: 23 | S96: 24 | T96: 25 | U96: 26 | V96: 27
N97: Luz Adriana Gordillo
B98: OCTUBRE | I98: OCTUBRE | P98: OCTUBRE
B99: 30 | C99: 1 | D99: 2 | E99: 3 | F99: 4 | G99: 5 | H99: 6 | I99: 29 | J99: 30 | K99: 1 | L99: 2 | M99: 3 | N99: 4 | O99: 5 | P99: 28 | Q99: 29 | R99: 30 | S99: 1 | T99: 2 | U99: 3 | V99: 4
G100: Marbel
B101: 7 | C101: 8 | D101: 9 | E101: 10 | F101: 11 | G101: 12 | H101: 13 | I101: 6 | J101: 7 | K101: 8 | L101: 9 | M101: 10 | N101: 11 | O101: 12 | P101: 5 | Q101: 6 | R101: 7 | S101: 8 | T101: 9 | U101: 10 | V101: 11
B102: Marbel | N102: Oscar Gómez | O102: Daniela Saa
B103: 14 | C103: 15 | D103: 16 | E103: 17 | F103: 18 | G103: 19 | H103: 20 | I103: 17 | J103: 14 | K103: 15 | L103: 16 | M103: 17 | N103: 18 | O103: 19 | P103: 12 | Q103: 13 | R103: 14 | S103: 15 | T103: 16 | U103: 17 | V103: 18
...

Sheet ESTADO DE RESULTADO
A1: Estado de resultado integral 2024
A2: Código cuenta contable | B2: Nombre cuenta contable | C2: ENERO | D2: FEBRERO | E2: MARZO | F2: ABRIL | G2: MAYO | H2: JUNIO | I2: JULIO | J2: AGOSTO | K2: SEPTIEMBRE | L2: OCTUBRE | M2: NOVIEMBRE | N2: DICIEMBRE | O2: ACUMULADO
B3: Ingresos por alquileres | K3: =+'Ingresos _ Egresos 2024'!E10 -> 3450000 | L3: =+'Ingresos _ Egresos 2024'!E26 -> 6150000 | M3: =+'Ingresos _ Egresos 2024'!E41 -> 4912598 | N3: =+'Ingresos _ Egresos 2024'!E55 -> 6099704.7 | O3: =SUM(K3:N3) -> 20612303
B4: Utilidad acumulada del periodo anterior | K4: 0 | L4: 0 | M4: 0 | N4: 0 | O4: =SUM(K4:N4) -> 0
B5: Egresos | K5: =+'Ingresos _ Egresos 2024'!K10 -> 3403276.4 | L5: =+'Ingresos _ Egresos 2024'!K26 -> 5126730.1 | M5: =+'Ingresos _ Egresos 2024'!K41 -> 4892520.7 | N5: =+'Ingresos _ Egresos 2024'!K55 -> 6912673.1 | O5: =SUM(K5:N5) -> 20335200
B6: Comisiones | K6: 140000 | L6: =960000+560000+180000 -> 1700000 | N6: 600000 | O6: =SUM(K6:N6) -> 2440000
B7: Nómina Jairo | K7: =700000+700000 -> 1400000 | L7: =700000+700000 -> 1400000 | M7: =700000+700000 -> 1400000 | N7: =700000+700000+2968000 -> 4368000 | O7: =SUM(K7:N7) -> 8568000
B8: Nómina Omaira | L8: =400000+400000 -> 800000 | M8: 400000 | N8: 400000 | O8: =SUM(K8:N8) -> 1600000
B9: Energía | K9: 1541700 | M9: 894240 | O9: =SUM(K9:N9) -> 2435940
B10: Internet | K10: =103000+51500 -> 154500 | L10: 51500 | M10: 51500 | N10: 51500 | O10: =SUM(K10:N10) -> 309000
B11: Agua | O11: =SUM(K11:N11) -> 0
B12: Gas | M12: 330000 | N12: 338000 | O12: =SUM(K12:N12) -> 668000
B13: Comida perros | K13: 120000 | O13: =SUM(K13:N13) -> 120000
B14: Predial 2024 | M14: 648810 | O14: =SUM(K14:N14) -> 648810
B15: Materiales para guadañar | L15: 150000 | M15: 150000 | O15: =SUM(K15:N15) -> 300000
B16: Quimicos Piscina | L16: 216702 | N16: 316515 | O16: =SUM(K16:N16) -> 533217
B17: Productos aseo | M17: 50000 | O17: =SUM(K17:N17) -> 50000
B18: Mantenimientos generales | L18: =170000+600000 -> 770000 | M18: 400000 | N18: 350000 | O18: =SUM(K18:N18) -> 1520000
B19: Avalúo | M19: 500000 | N19: 450000 | O19: =SUM(K19:N19) -> 950000
B20: Documentos | M20: 20900 | O20: =SUM(K20:N20) -> 20900
B21: Gastos bancarios | K21: =+'Ingresos _ Egresos 2024'!K9 -> 47076.43 | L21: =+'Ingresos _ Egresos 2024'!K25 -> 38528.12 | M21: =+'Ingresos _ Egresos 2024'!K40 -> 47070.66 | N21: =+'Ingresos _ Egresos 2024'!K54 -> 38658.12 | O21: =SUM(K21:N21) -> 171333.33
B22: Utilidad(+)/Pérdida del ejercicio(-) | K22: =+K3-K5 -> 46723.57 | L22: =+L3-L5 -> 1023269.9 | M22: =+M3-M5 -> 20077.34 | N22: =+N3-N5 -> -812968.45 | O22: =SUM(K22:N22) -> 277102.34
A25: Estado de resultado integral 2025
A26: Código cuenta contable | B26: Nombre cuenta contable | C26: ENERO | D26: FEBRERO | E26: MARZO | F26: ABRIL | G26: MAYO | H26: JUNIO | I26: JULIO | J26: AGOSTO | K26: SEPTIEMBRE | L26: OCTUBRE | M26: NOVIEMBRE | N26: DICIEMBRE | O26: ACUMULADO
B27: Ingresos por alquileres | C27: =+'Ingresos_Egresos 2025'!E10 -> 2595458 | D27: =+'Ingresos_Egresos 2025'!E23 -> 3353136 | E27: =+'Ingresos_Egresos 2025'!E39 -> 4845556 | F27: =+'Ingresos_Egresos 2025'!E56 -> 5525117 | G27: =+'Ingresos_Egresos 2025'!E69 -> 6068360 | H27: =+'Ingresos_Egresos 2025'!E89 -> 7846087 | I27: =+'Ingresos_Egresos 2025'!E112 -> 2972621 | J27: =+'Ingresos_Egresos 2025'!E128 -> 8291225 | K27: =+'Ingresos_Egresos 2025'!E148 -> 5371597 | L27: =+'Ingresos_Egresos 2025'!E162 -> 2275000 | M27: =+'Ingresos_Egresos 2025'!E183 -> 2073165 | N27: =+'Ingresos_Egresos 2025'!E202 -> 8665973 | O27: =SUM(C27:N27) -> 59883295
B28: Utilidad acumulada del periodo anterior | C28: =+O22 -> 277102.34 | O28: =SUM(C28:N28) -> 277102.34
B29: Egresos | C29: =+'Ingresos_Egresos 2025'!K10 -> 2548956.2 | D29: =+'Ingresos_Egresos 2025'!K23 -> 4308663.9 | E29: =+'Ingresos_Egresos 2025'!K39 -> 3650057.8 | F29: =+'Ingresos_Egresos 2025'!K56 -> 7473007.9 | G29: =+'Ingresos_Egresos 2025'!K69 -> 4282672.5 | H29: =+'Ingresos_Egresos 2025'!K89 -> 5830790.7 | I29: =+'Ingresos_Egresos 2025'!K112 -> 9270014.5 | J29: =+'Ingresos_Egresos 2025'!K128 -> 2846461.1 | K29: =+'Ingresos_Egresos 2025'!K148 -> 7744737.6 | L29: =+'Ingresos_Egresos 2025'!K162 -> 2604829 | M29: =+'Ingresos_Egresos 2025'!K183 -> 3871154 | N29: =+'Ingresos_Egresos 2025'!K202 -> 5266594.1 | O29: =SUM(C29:N29) -> 59697939
B30: Comisiones | C30: 180000 | D30: 140000 | E30: 180000 | F30: 900000 | H30: 380000 | I30: =576560+190000+180000 -> 946560 | J30: 180000 | K30: =180000+180000+380000+380000+180000 -> 1300000 | L30: 180000 | M30: =380000+180000 -> 560000 | O30: =SUM(C30:N30) -> 4946560
B31: Nómina Jairo | C31: =750000+750000 -> 1500000 | D31: =750000+750000 -> 1500000 | E31: =750000+750000 -> 1500000 | F31: =750000+750000 -> 1500000 | G31: =750000+750000 -> 1500000 | H31: =1500000+750000 -> 2250000 | I31: =750000+750000 -> 1500000 | J31: =750000+750000 -> 1500000 | K31: =750000+750000+2163750 -> 3663750 | L31: =711750+711750 -> 1423500 | M31: =711750+711750 -> 1423500 | N31: =711750+711750+711750 -> 2135250 | O31: =SUM(C31:N31) -> 21396000
B32: Nómina Omaira | C32: 400000 | D32: 400000 | E32: 400000 | F32: 400000 | G32: 500000 | H32: =200000+400000 -> 600000 | I32: 500000 | J32: 500000 | K32: 500000 | L32: 427050 | M32: 474500 | N32: 921950 | O32: =SUM(C32:N32) -> 6023500
B33: Energía | D33: 1031790 | F33: 755920 | H33: =945650 -> 945650 | I33: 789700 | K33: 647390 | N33: 607800 | O33: =SUM(C33:N33) -> 4778250
B34: Internet | C34: 51500 | D34: 51500 | E34: 51500 | F34: 51500 | G34: 51500 | H34: 51500 | I34: 51500 | J34: 51500 | K34: 51500 | L34: 51500 | M34: 51500 | N34: 51500 | O34: =SUM(C34:N34) -> 618000
B35: Agua | H35: =87400+234800 -> 322200 | K35: 87400 | O35: =SUM(C35:N35) -> 409600
B36: Gas | E36: 102000 | G36: 230000 | H36: =98000+210000 -> 308000 | J36: 305000 | L36: 210000 | M36: 95000 | N36: 210000 | O36: =SUM(C36:N36) -> 1460000
B37: Comida perros | O37: =SUM(C37:N37) -> 0
B38: Predial 2025 | E38: 353364 | O38: =SUM(C38:N38) -> 353364
B39: Materiales para guadañar | C39: 112900 | F39: =+'Ingresos_Egresos 2025'!K43+'Ingresos_Egresos 2025'!K44+'Ingresos_Egresos 2025'!K45 -> 158100 | G39: 150000 | H39: 150000 | I39: 150000 | J39: 150000 | L39: 168503 | M39: =81467+150000 -> 231467 | N39: 150000 | O39: =SUM(C39:N39) -> 1420970
B40: Quimicos Piscina | D40: =+'Ingresos_Egresos 2025'!K14 -> 367817 | G40: 518829 | I40: 447617 | K40: 519519 | N40: 619611 | O40: =SUM(C40:N40) -> 2473393
B41: Productos aseo | C41: =158750+107150 -> 265900 | F41: 80000 | I41: =204700+50000 -> 254700 | M41: =121000+163000 -> 284000 | O41: =SUM(C41:N41) -> 884600
B42: Mantenimientos generales | D42: =591003+187900 -> 778903 | F42: =+'Ingresos_Egresos 2025'!K48+'Ingresos_Egresos 2025'!K51+'Ingresos_Egresos 2025'!K42 -> 3597500 | G42: =1272200+12800 -> 1285000 | H42: =400000+160000+50000+107000+76500 -> 793500 | I42: =300000+1000000+700000+100000+1000000+1000000+500000 -> 4600000 | J42: 130000 | K42: =224800+719200 -> 944000 | L42: 100000 | N42: =50000+80000 -> 130000 | O42: =SUM(C42:N42) -> 12358903
B43: Avalúo | O43: =SUM(C43:N43) -> 0
B44: Seguridad Social | M44: =609505 -> 609505 | N44: =378220 -> 378220 | O44: =SUM(C44:N44) -> 987725
B45: Trámites e impuestos | E45: =786645+51900+120000+57300 -> 1015845 | M45: 68000 | O45: =SUM(C45:N45) -> 1083845
B46: Gastos bancarios | C46: =+'Ingresos_Egresos 2025'!K9 -> 38656.25 | D46: =+'Ingresos_Egresos 2025'!K22 -> 38653.87 | E46: =+'Ingresos_Egresos 2025'!K38 -> 47348.84 | F46: =+'Ingresos_Egresos 2025'!K55 -> 29987.89 | G46: =+'Ingresos_Egresos 2025'!K68 -> 47343.55 | H46: =+'Ingresos_Egresos 2025'!K88 -> 29940.74 | I46: =+'Ingresos_Egresos 2025'!K111 -> 29937.47 | J46: =+'Ingresos_Egresos 2025'!K122 -> 29961.1 | K46: =+'Ingresos_Egresos 2025'!K147 -> 31178.64 | L46: =+'Ingresos_Egresos 2025'!K161 -> 44276 | M46: =+'Ingresos_Egresos 2025'!K182 -> 73681.96 | N46: =+'Ingresos_Egresos 2025'!K201 -> 62263.11 | O46: =SUM(C46:N46) -> 503229.42
B47: Utilidad(+)/Pérdida del ejercicio(-) | C47: =+C27+C28-C29 -> 323604.09 | D47: =+D27+D28-D29 -> -955527.87 | E47: =+E27+E28-E29 -> 1195498.2 | F47: =+F27+F28-F29 -> -1947890.9 | G47: =+G27+G28-G29 -> 1785687.5 | H47: =+H27+H28-H29 -> 2015296.3 | I47: =+I27+I28-I29 -> -6297393.5 | J47: =+J27+J28-J29 -> 5444763.9 | ... N47: =+N27+N28-N29 -> 3399378.9 | O47: =SUM(C47:N47) -> 462457.92
A57: Estado de resultado integral 2026
A58: Código cuenta contable | B58: Nombre cuenta contable | C58: ENERO | D58: FEBRERO | E58: MARZO | F58: ABRIL | G58: MAYO | H58: JUNIO | I58: JULIO | J58: AGOSTO | K58: SEPTIEMBRE | L58: OCTUBRE | M58: NOVIEMBRE | N58: DICIEMBRE | O58: ACUMULADO
B59: Ingresos por alquileres | C59: =+'Ingresos_Egresos 2026'!E32 -> 8564892 | O59: =SUM(C59:N59) -> 8564892
B60: Utilidad acumulada del periodo anterior | C60: =+O47 -> 462457.92 | O60: =SUM(C60:N60) -> 462457.92
B61: Egresos | C61: =+'Ingresos_Egresos 2026'!K32 -> 9893337.6 | O61: =SUM(C61:N61) -> 9893337.6
B62: Comisiones | C62: =760000+380000+125000 -> 1265000 | O62: =SUM(C62:N62) -> 1265000
B63: Nómina Jairo | C63: =875453+875453 -> 1750906 | O63: =SUM(C63:N63) -> 1750906
B64: Nómina Omaira | C64: 758732 | O64: =SUM(C64:N64) -> 758732
B65: Energía | C65: 738970 | O65: =SUM(C65:N65) -> 738970
B66: Internet | C66: 51500 | O66: =SUM(C66:N66) -> 51500
B67: Agua | C67: =174800+98000 -> 272800 | O67: =SUM(C67:N67) -> 272800
B68: Gas | C68: =210000+95000 -> 305000 | O68: =SUM(C68:N68) -> 305000
B69: Comida perros | O69: =SUM(C69:N69) -> 0
B70: Predial 2026 | O70: =SUM(C70:N70) -> 0
B71: Materiales para guadañar | C71: 180000 | O71: =SUM(C71:N71) -> 180000
B72: Quimicos Piscina | O72: =SUM(C72:N72) -> 0
B73: Productos aseo | C73: 349200 | O73: =SUM(C73:N73) -> 349200
B74: Mantenimientos generales | C74: =927500+100000+100000+170000+216000+299285+90000+450000+357700 -> 2710485 | O74: =SUM(C74:N74) -> 2710485
B75: Avalúo | O75: =SUM(C75:N75) -> 0
B76: Seguridad Social | C76: =391220+569848.22+454020 -> 1415088.2 | O76: =SUM(C76:N76) -> 1415088.2
B77: Trámites e impuestos | C77: 22000 | O77: =SUM(C77:N77) -> 22000
B78: Gastos bancarios | C78: =+'Ingresos_Egresos 2026'!K31 -> 73656.34 | O78: =SUM(C78:N78) -> 73656.34
B79: Utilidad(+)/Pérdida del ejercicio(-) | C79: =+C59+C60-C61 -> -865987.64 | D79: =+D59+D60-D61 -> 0 | E79: =+E59+E60-E61 -> 0 | F79: =+F59+F60-F61 -> 0 | G79: =+G59+G60-G61 -> 0 | H79: =+H59+H60-H61 -> 0 | I79: =+I59+I60-I61 -> 0 | J79: =+J59+J60-J61 -> 0 | ... N79: =+N59+N60-N61 -> 0 | O79: =SUM(C79:N79) -> -865987.64

Sheet Ingresos_Egresos 2026
B2: INGRESOS | C2: FECHA | D2: CONCEPTO | E2: ABONO | F2: SALDO | H2: EGRESOS | I2: FECHA | J2: CONCEPTO | K2: VALOR | M2: UTILIDAD
B3: ENERO | C3: 46024 | D3: Alquiler Santiago Benavides 6 al 12 enero | E3: 2000000 | H3: ENERO | I3: 46024 | J3: Pago Contribución Parafiscal- FONTUR 2025 | K3: 22000 | M3: =+E32-K32 -> -1328445.6
C4: 46027 | D4: Airbnb Alquiler Nicolay Gil 3 - 4 enero | E4: 828315 | I4: 46024 | J4: Seguridad social diciembre | K4: 391220
C5: 46030 | D5: Alquiler Santiago Benavides 6 al 12 enero | E5: 1800000 | I5: 46024 | J5: Pago Agua septiembre - octubre | K5: 87400
C6: 46030 | D6: Alquiler Santiago Benavides 6 al 12 enero deposito | E6: 200000 | I6: 46024 | J6: Pago Agua noviembre - diciembre | K6: 87400
C7: 46034 | D7: Alquiler Yaneth Rodríguez 24 al 25 enero | E7: 475000 | I7: 46024 | J7: Comisión Alquiler Santiago Benavides 6 al 12 enero | K7: =3800000*0.2 -> 760000
C8: 46035 | D8: Alquiler Santiago Benavides 6 al 12 enero deposito | E8: -200000 | I8: 46024 | J8: Compra de cobijas y almohadas | K8: 927500
C9: 46037 | D9: Alquiler Natalia Acevedo 31 ene al 1 feb | E9: 475000 | I9: 46027 | J9: Materiales para guadañar | K9: 180000
C10: 46038 | D10: Alquiler Luceyda Londoño 7 al 8 Feb | E10: 1000000 | I10: 46027 | J10: Aseo adicional sábado 3 enero | K10: 100000
C11: 46042 | D11: Airbnb AlquilerAndrés Santiago 17 - 18 enero | E11: 711577 | I11: 46027 | J11: Aseo adicional lunes 5 enero | K11: 100000
C12: 46044 | D12: Alquiler Yaneth Rodríguez 24 al 25 enero | E12: 475000 | I12: 46028 | J12: Productos de aseo | K12: 349200
C13: 46044 | D13: Alquiler Yaneth Rodríguez 24 al 25 enero deposito | E13: 200000 | I13: 46031 | J13: Pipeta de gas para Jacuzzi | K13: 210000
C14: 46048 | D14: Alquiler Yaneth Rodríguez 24 al 25 enero deposito | E14: -200000 | I14: 46032 | J14: Energia | K14: 738970
C15: 46053 | D15: Alquiler Natalia Acevedo 31 ene al 1 feb | E15: =475000+125000 -> 600000 | I15: 46034 | J15: Pago de Cesantias Jairo y Omaira | K15: 569848.22
C16: 46053 | D16: Alquiler Natalia Acevedo 31 ene al 1 feb deposito | E16: 200000 | I16: 46035 | J16: Arreglo lavadora | K16: 170000
I17: 46036 | J17: Materiales arreglo tuberia rio / Compra guaya | K17: 216000
I18: 46037 | J18: Jairo Primera quincena | K18: 875453
I19: 46038 | J19: Mangueras | K19: 299285
I20: 46038 | J20: Comisión Alquiler alquileres 24 y 31 de enero | K20: 380000
I21: 46038 | J21: Pipeta de gas para cocina | K21: 95000
I22: 46043 | J22: Seguridad social enero | K22: 454020
I23: 46042 | J23: Internet | K23: 51500
I24: 46044 | J24: Arreglo eléctrico | K24: 90000
I25: 46044 | J25: Agua enero | K25: 98000
I26: 46045 | J26: Mantenimiento Jacuzzi | K26: 450000
I27: 46052 | J27: Jairo Segunda quincena | K27: 875453
I28: 46052 | J28: Salario Omaira | K28: 758732
... I31: 46053 | J31: Gastos bancarios | K31: 73656.34
D32: TOTAL INGRESO | E32: =SUM(E3:E31) -> 8564892 | J32: TOTAL EGRESOS | K32: =SUM(K3:K31) -> 9893337.6 | N32: =+M3-'ESTADO DE RESULTADO'!C79 -> -462457.92

Sheet Ingresos_Egresos 2025
B1: INGRESOS | C1: FECHA | D1: CONCEPTO | E1: ABONO | F1: SALDO | H1: EGRESOS | I1: FECHA | J1: CONCEPTO | K1: VALOR | M1: UTILIDAD
B2: ENERO | C2: 45659 | D2: Alquiler Marly Andrea 11-12 ene | E2: 450000 | H2: ENERO | I2: 45659 | J2: Comisión Alquiler Marly Andrea 11-12 ene | K2: 180000 | M2: =+E10-K10 -> 46501.75
C3: 45659 | D3: Alquiler Marly Andrea 11-12 ene depósito | E3: 200000 | I3: 45677 | J3: Internet | K3: 51500
C4: 45661 | D4: Alquiler Marly Andrea 11-12 ene depósito | E4: -200000 | I4: 45677 | J4: Productos aseo | K4: 265900
C5: 45669 | D5: Alquiler Marly Andrea 11-12 ene daño silla | E5: 100000 | I5: 45678 | J5: Primera quincena enero Jairo | K5: 750000
C6: 45671 | D6: Alquiler Angela Sierra 15-16 feb | E6: 120000 | I6: 45681 | J6: Reintegro materiales para guadañar | K6: =77900+35000 -> 112900
C7: 45678 | D7: Airbnb Catherine Tabares 18 - 19 ene | E7: 811411 | I7: 45687 | J7: Segunda quincena enero Jairo | K7: 750000
C8: 45684 | D8: Airbnb Hernando Diaz 25 - 26 ene | E8: 764047 | I8: 45688 | J8: Pago enero Omaira López | K8: 400000
C9: 45688 | D9: Alquiler Juián Betancourth 1- 2 feb | E9: 350000 | I9: 45688 | J9: Gastos bancarios | K9: 38656.25
D10: TOTAL INGRESO | E10: =SUM(E2:E9) -> 2595458 | J10: TOTAL EGRESOS | K10: =SUM(K2:K9) -> 2548956.2 | N10: =+M2-'ESTADO DE RESULTADO'!C47 -> -277102.34
B12: INGRESOS | C12: FECHA | D12: CONCEPTO | E12: ABONO | F12: SALDO | H12: EGRESOS | I12: FECHA | J12: CONCEPTO | K12: VALOR | M12: UTILIDAD
B13: FEBRERO | C13: 45689 | D13: Alquiler Juián Betancourth 1- 2 feb | E13: 350000 | H13: FEBRERO | I13: 45689 | J13: Alquiler Juián Betancourth 1- 2 feb comisión | K13: =+(E9+E13)*0.2 -> 140000 | M13: =+E23-K23 -> -955527.87
C14: 45689 | D14: Alquiler Juián Betancourth 1- 2 feb deposito | E14: 200000 | I14: 45694 | J14: Quimicos piscina | K14: 367817
C15: 45690 | D15: Alquiler Juián Betancourth 1- 2 feb deposito | E15: -200000 | I15: 45704 | J15: Primera quincena febrero Jairo | K15: 750000
C16: 45693 | D16: Alquiler Hebert Adolfo Bermudez 15-16 mar | E16: 200000 | I16: 45708 | J16: Internet febrero | K16: 51500
C17: 45698 | D17: Airbnb Valentina Tabares 8-9 feb | E17: 816108 | I17: 45712 | J17: Energía | K17: 1031790
C18: 45702 | D18: Alquiler Angela Sierra 15-16 feb | E18: 145000 | I18: 45716 | J18: Segunda quincena febrero Jairo | K18: 750000
C19: 45708 | D19: Alquiler Paola Laguna 1-2 mar | E19: 400000 | I19: 45716 | J19: Pago febrero Omaira López | K19: 400000
C20: 45712 | D20: Airbnb Maria Camila 22-23 feb | E20: 842028 | I20: 45716 | J20: Materiales arreglo pisicina | K20: 591003
C21: 45715 | D21: Alquiler Paola Laguna 1-2 mar | E21: 400000 | I21: 45716 | J21: Mano de obra mantenimiento pisicina | K21: 187900
C22: 45716 | D22: Alquiler Hebert Adolfo Bermudez 15-16 mar | E22: 200000 | I22: 45716 | J22: Gastos bancarios | K22: 38653.87
D23: TOTAL INGRESO | E23: =SUM(E13:E22) -> 3353136 | J23: TOTAL EGRESOS | K23: =SUM(K13:K22) -> 4308663.9 | N23: =+M13-'ESTADO DE RESULTADO'!D47 -> 0
B25: INGRESOS | C25: FECHA | D25: CONCEPTO | E25: ABONO | F25: SALDO | H25: EGRESOS | I25: FECHA | J25: CONCEPTO | K25: VALOR | M25: UTILIDAD
B26: MARZO | C26: 45726 | D26: Alquiler Jaime Soto 21 al 27 de Abr | E26: 1850000 | H26: MARZO | I26: 45719 | J26: Gastos notariales levantamiento usufructo | K26: 381945 | M26: =+E39-K39 -> 1195498.2
C27: 45730 | D27: Alquiler Hebert Adolfo Bermudez 15-16 mar | E27: 500000 | I27: 45723 | J27: Boleta fiscal levantamiento usufructo | K27: 404700
C28: 45741 | D28: Stephanie Gasca Airbnb 22-24 mar | E28: 1658969 | I28: 45727 | J28: Cancelación en superintendencia de notariado | K28: 51900
C29: 45747 | D29: Camilo Lucero Airbnb 29-30 mar | E29: 836587 | I29: 45727 | J29: Gastos de escritura nueva | K29: 120000
I30: 45730 | J30: Acto de cancelación de omisión | K30: 57300
I31: 45730 | J31: Alquiler Hebert Adolfo Bermudez 15-16 mar comisión | K31: 180000
I32: 45736 | J32: internet marzo | K32: 51500
I33: 45741 | J33: Primera quincena marzo Jairo | K33: 750000
I34: 45741 | J34: Predial 2025 | K34: 353364
I35: 45743 | J35: Pipeta de gas de la cocina | K35: 102000
I36: 45747 | J36: Segunda quincena marzo Jairo | K36: 750000
I37: 45747 | J37: Pago marzo Omaira López | K37: 400000
I38: 45747 | J38: Gastos bancarios | K38: 47348.84
D39: TOTAL INGRESO | E39: =SUM(E26:E37) -> 4845556 | J39: TOTAL EGRESOS | K39: =SUM(K26:K38) -> 3650057.8 | N39: =+M26-'ESTADO DE RESULTADO'!E47 -> 0
B41: INGRESOS | C41: FECHA | D41: CONCEPTO | E41: ABONO | F41: SALDO | H41: EGRESOS | I41: FECHA | J41: CONCEPTO | K41: VALOR | M41: UTILIDAD
B42: ABRIL | C42: 45766 | D42: Alquiler Jaime Soto 21 al 27 de Abr | E42: 2650000 | H42: ABRIL | I42: 45766 | J42: Compra de toallas | K42: 341900 | M42: =+E56-K56 -> -1947890.9
C43: 45766 | D43: Alquiler Jaime Soto 21 al 27 de Abr déposito | E43: 200000 | I43: 45766 | J43: Compra de aceite para guadañar | K43: 63000
C44: 45766 | D44: Alquiler Natalia Acevedo 24-25 Mayo | E44: 400000 | I44: 45766 | J44: Compra de gasolina para guadañar | K44: 78750
C45: 45768 | D45: Jhon Zabala Airbnb 17 - 21 abtil | E45: 2475117 | I45: 45766 | J45: Transporte compras | K45: =500000-K42-K43-K44 -> 16350
C46: 45789 | D46: Alquiler Jaime Soto 21 al 27 de Abr déposito | E46: -200000 | I46: 45766 | J46: Primera quincena abril Jairo | K46: 750000
I47: 45766 | J47: Energía | K47: 755920
I48: 45767 | J48: Ropa de cama | K48: 966800
I49: 45768 | J49: Comisión Alquiler Jaime Soto 21 al 27 de Abr | K49: 900000
I50: 45768 | J50: Aseo adicional | K50: 80000
I51: 45768 | J51: Compra de guadaña | K51: 2288800
I52: 45779 | J52: Internet abril | K52: 51500
I53: 45779 | J53: Pago Omaira mes de abril | K53: 400000
I54: 45782 | J54: Segundo quincena abril Jairo | K54: 750000
I55: 45777 | J55: Gastos bancarios | K55: 29987.89
D56: TOTAL INGRESO | E56: =SUM(E42:E55) -> 5525117 | J56: TOTAL EGRESOS | K56: =SUM(K42:K55) -> 7473007.9 | N56: =+M42-'ESTADO DE RESULTADO'!F47 -> 0
B57: INGRESOS | C57: FECHA | D57: CONCEPTO | E57: ABONO | F57: SALDO | H57: EGRESOS | I57: FECHA | J57: CONCEPTO | K57: VALOR | M57: UTILIDAD
B58: MAYO | C58: 45779 | D58: Erika Airbnb 30 abr - 1 may | E58: 752288 | H58: MAYO | I58: 45779 | J58: Pipeta de gas piscina | K58: 230000 | M58: =+E69-K69 -> 1785687.5
C59: 45782 | D59: Mayerlin Airbnb 3 - 4 may | E59: 758334 | I59: 45789 | J59: Materiales pisicina | K59: 518829
C60: 45789 | D60: Richard Airbnb 10-11 may | E60: 753624 | I60: 45796 | J60: Primera quincena mayo Jairo | K60: 750000
C61: 45796 | D61: Santiago Benavides Airbnb 16-19 may | E61: 2234114 | I61: 45796 | J61: Aceite y nylon para guadañar | K61: 63000
C62: 45799 | D62: Alquiler Maricela 21-23 Jun | E62: 1250000 | I62: 45796 | J62: Gasolina para guadañar | K62: 87000
C63: 45800 | D63: Alquiler Natalia Acevedo 24-25 Mayo | E63: 320000 | I63: 45797 | J63: Compra menaje | K63: 1272200
I64: 45797 | J64: Transporte menaje homecenter | K64: =1285000-K63 -> 12800
I65: 45797 | J65: Internet mayo | K65: 51500
I66: 45807 | J66: Segunda quncena mayo Jairo | K66: 750000
I67: 45807 | J67: Pago Omaira mes de mayo | K67: 500000
I68: 45808 | J68: Gastos bancarios | K68: 47343.55
D69: TOTAL INGRESO | E69: =SUM(E58:E68) -> 6068360 | J69: TOTAL EGRESOS | K69: =SUM(K58:K68) -> 4282672.5 | N69: =+M58-'ESTADO DE RESULTADO'!G47 -> 0
B71: INGRESOS | C71: FECHA | D71: CONCEPTO | E71: ABONO | F71: SALDO | H71: EGRESOS | I71: FECHA | J71: CONCEPTO | K71: VALOR | M71: UTILIDAD
B72: JUNIO | C72: 45810 | D72: Camilo Airbnb 31 may - 1 jun | E72: 754387 | H72: JUNIO | I72: 45810 | J72: Energía | K72: =945650/2 -> 472825 | M72: =+E89-K89 -> 2015296.3
C73: 45813 | D73: Alquiler booking Adriana Herrera | E73: 1225500 | I73: 45812 | J73: Pipeta de gas cocina | K73: 98000
C74: 45814 | D74: Alquiler Juan David Vidal 12-15 Jun | E74: 1425000 | I74: 45813 | J74: Energía | K74: =945650/2 -> 472825
C75: 45820 | D75: Alquiler Juan David Vidal 12-15 Jun | E75: 375000 | I75: 45823 | J75: Pago nómina y prima de junio Jairo | K75: 1500000
C76: 45824 | D76: Alquiler Victor Manuel 19-20 Jul | E76: 475000 | I76: 45823 | J76: Materiales para guadañar | K76: 150000
C77: 45827 | D77: Alquiler Maricela 21-23 Jun | E77: 650000 | I77: 45823 | J77: Prima Doña Omaira | K77: 200000
C78: 45827 | D78: Alquiler Maricela 21-23 Jun deposito | E78: 200000 | I78: 45825 | J78: Agua de mayo y junio 2025 | K78: 87400
C79: 45832 | D79: Alquiler Maricela 21-23 Jun deposito | E79: -200000 | I79: 45825 | J79: Agua de enero - abril 2025 | K79: 234800
C80: 45835 | D80: Alquiler booking Alejandra Rivera 27 - 30 junio | E80: 2941200 | I80: 45825 | J80: Reparación motor Jacuzzi | K80: 400000
I81: 45828 | J81: Internet | K81: 51500
I82: 45828 | J82: Comisión Alquiler Maricela 21-23 Jun | K82: 380000
I83: 45829 | J83: Reparación motor Jacuzzi | K83: 317000
I84: 45829 | J84: Compra de rejilla para jacuzzi | K84: 76500
I85: 45835 | J85: Pipeta gas piscina | K85: 210000
I86: 45838 | J86: Pago segunda nomina Junio Jairo | K86: 750000
I87: 45838 | J87: Pago nómina junio Omaira | K87: 400000
I88: 45838 | J88: Gastos bancarios | K88: 29940.74
D89: TOTAL INGRESO | E89: =SUM(E72:E88) -> 7846087 | J89: TOTAL EGRESOS | K89: =SUM(K72:K88) -> 5830790.7 | N89: =+M72-'ESTADO DE RESULTADO'!H47 -> 0
B91: INGRESOS | C91: FECHA | D91: CONCEPTO | E91: ABONO | F91: SALDO | H91: EGRESOS | I91: FECHA | J91: CONCEPTO | K91: VALOR | M91: UTILIDAD
B92: JULIO | C92: 45845 | D92: Alquiler Airbnb Lorena 5-6 Julio | E92: 840268 | H92: JULIO | I92: 45839 | J92: Productos aseo | K92: 204700 | M92: =+E112-K112 -> -6297393.5
C93: 45852 | D93: Alquiler Airbnb Mario 12-13 julio | E93: 757353 | I93: 45840 | J93: Bolsas de basura + transporte | K93: 50000
C94: 45853 | D94: Alquiler Yubis Saavedra 26-27 julio | E94: 450000 | I94: 45844 | J94: Comisión Booking mes de Junio | K94: 576560
C95: 45856 | D95: Alquiler Victor Manuel 19-20 Jul | E95: 475000 | I95: 45847 | J95: Pago arreglo de la lavadora | K95: 300000
C96: 45856 | D96: Alquiler Victor Manuel 19-20 Jul deposito | E96: 200000 | I96: 45853 | J96: Pago primera nomina Julio Jairo | K96: 750000
C97: 45859 | D97: Alquiler Victor Manuel 19-20 Jul deposito | E97: -200000 | I97: 45854 | J97: Materiales para guadañar | K97: 150000
C98: 45863 | D98: Alquiler Yubis Saavedra 26-27 julio | E98: 450000 | I98: 45855 | J98: Energía | K98: 789700
C99: 45863 | D99: Alquiler Yubis Saavedra 26-27 julio deposito | E99: 200000 | I99: 45856 | J99: Alquiler Victor Manuel 19-20 Jul comisión | K99: 190000
C100: 45866 | D100: Alquiler Yubis Saavedra 26-27 julio deposito | E100: -200000 | I100: 45858 | J100: Anticipo fragua de la pisicina | K100: 1000000
I101: 45863 | J101: Alquiler de la motobomba | K101: 700000
I102: 45863 | J102: Internet | K102: 51500
I103: 45863 | J103: Alquiler mangueras llenado pisicina | K103: 100000
I104: 45863 | J104: Quimicos piscina | K104: 447617
I105: 45863 | J105: Alquiler Yubis Saavedra 26-27 julio comisión | K105: =+(E94+E98)*0.2 -> 180000
...

Sheet Ingresos _ Egresos 2024
B1: INGRESOS | C1: FECHA | D1: CONCEPTO | E1: ABONO | F1: SALDO | H1: EGRESOS | I1: FECHA | J1: CONCEPTO | K1: VALOR | M1: UTILIDAD
B2: SEPTIEMBRE | C2: 45545 | D2: Alquiler Marbel 5-11Oct | E2: 2300000 | H2: SEPTIEMBRE | I2: 45545 | J2: Energía | K2: 1541700 | M2: =+E10-K10 -> 46723.57
C3: 45546 | D3: Alquiler Viviana 14-15 Sep | E3: 700000 | I3: 45546 | J3: Internet Julio - Agosto | K3: =51500*2 -> 103000
C4: 45546 | D4: Alquiler Viviana 14-15 Sep déposito | E4: 200000 | I4: 45546 | J4: Comisión Viviana 14-15 Sep | K4: 140000
C5: 45550 | D5: Alquiler Viviana 14-15 Sep déposito | E5: -200000 | I5: 45549 | J5: Primera quincena septiembre Jairo | K5: 700000
C6: 45555 | D6: Alquiler Diego Quintero 31 - 2 enero | E6: 450000 | I6: 45555 | J6: Internet Septiembre | K6: 51500
C7: 45555 | D7: Alquiler Erly Aragon 21-22 Sep déposito | E7: 200000 | I7: 45561 | J7: Comida Sasha | K7: 120000
C8: 45557 | D8: Alquiler Erly Aragon 21-22 Sep déposito | E8: -200000 | I8: 45565 | J8: Segunda quincena septiembre Jairo | K8: 700000
I9: 45565 | J9: Gastos bancarios | K9: 47076.43
D10: TOTAL INGRESO | E10: =SUM(E2:E9) -> 3450000 | J10: TOTAL EGRESOS | K10: =SUM(K2:K9) -> 3403276.4 | N10: =+M2-'ESTADO DE RESULTADO'!K22 -> 0
B12: INGRESOS | C12: FECHA | D12: CONCEPTO | E12: ABONO | F12: SALDO | H12: EGRESOS | I12: FECHA | J12: CONCEPTO | K12: VALOR | M12: UTILIDAD
B13: OCTUBRE | C13: 45569 | D13: Alquiler Mateo Vasquez 19 - 20 Oct | E13: 450000 | H13: OCTUBRE | I13: 45569 | J13: Pago septiembre Omaira López | K13: 400000 | M13: =+E26-K26 -> 1023269.9
C14: 45569 | D14: Alquiler Marbel 5-11Oct saldo | E14: 2500000 | I14: 45569 | J14: Comisión Marbel 5-11Oct depósito | K14: 960000
C15: 45569 | D15: Alquiler Marbel 5-11Oct depósito | E15: 200000 | I15: 45570 | J15: Quimicos piscina | K15: 216702
C16: 45576 | D16: Alquiler Marbel 5-11Oct depósito | E16: -200000 | I16: 45579 | J16: Materiales para guadañar | K16: 150000
C17: 45582 | D17: Alquiler Mateo Vasquez 19 - 20 Oct | E17: 450000 | I17: 45582 | J17: Primera quincena octubre Jairo | K17: 700000
C18: 45582 | D18: Alquiler Mateo Vasquez 19 - 20 Oct depósito | E18: 200000 | I18: 17 | J18: Comisión Mateo Vasquez 19 - 20 Oct | K18: =900000*0.2 -> 180000
C19: 45589 | D19: Alquiler Julián Laguna 26-27 Oct | E19: 850000 | I19: 45589 | J19: Arreglo uniones agua | K19: 170000
C20: 45590 | D20: Alquiler Valentina Tafur 14-15 Dic | E20: 900000 | I20: 45589 | J20: Internet octubre | K20: 51500
C21: 45590 | D21: Alquiler Mateo Vasquez 19-20 Oct depósito | E21: -200000 | I21: 45589 | J21: Adelanto Rito arreglo malla | K21: 600000
C22: 45591 | D22: Alquiler Andrés Quejada 2-4 Nov | E22: 1000000 | I22: 45591 | J22: Comisión Andrés Quejada y Valentina Tafur | K22: 560000
I23: 45596 | J23: Segunda quincena octubre Jairo | K23: 700000
I24: 45596 | J24: Pago octubre Omaira López | K24: 400000
I25: 45596 | J25: Gastos bancarios | K25: 38528.12
D26: TOTAL INGRESO | E26: =SUM(E13:E25) -> 6150000 | J26: TOTAL EGRESOS | K26: =SUM(K13:K25) -> 5126730.1 | N26: =+M13-'ESTADO DE RESULTADO'!L22 -> 0
B28: INGRESOS | C28: FECHA | D28: CONCEPTO | E28: ABONO | F28: SALDO | H28: EGRESOS | I28: FECHA | J28: CONCEPTO | K28: VALOR | M28: UTILIDAD
B29: NOVIEMBRE | C29: 45598 | D29: Alquiler Andrés Quejada 2-4 Nov | E29: 900000 | H29: NOVIEMBRE | I29: 45600 | J29: Saldo Rito arreglo malla | K29: 400000 | M29: =+E41-K41 -> 20077.34
C30: 45598 | D30: Alquiler Andrés Quejada 2-4 Nov depósito | E30: 200000 | I30: 45601 | J30: Predial 2024 | K30: 648810
C31: 45610 | D31: Alquiler Marly Andrea 11-12 ene | E31: 450000 | I31: 45611 | J31: Primera quincena noviembre Jairo | K31: 700000
C32: 45613 | D32: Alquiler Francia Navia 24-26 Dic | E32: 700000 | I32: 45614 | J32: Energía | K32: 894240
C33: 45614 | D33: Alquiler Francia Navia 24-26 Dic | E33: 600000 | I33: 45616 | J33: Materiales para guadañar y PH | K33: 200000
C34: 45618 | D34: Airbnb Evelyn 10 - 11 nov | E34: 776788 | I34: 45618 | J34: Internet noviembre | K34: 51500
C35: 45621 | D35: Paola Osorio Airbnb 22 - 23 nov | E35: 810810 | I35: 45623 | J35: Pipetas de gas 100 y 40 | K35: 330000
C36: 45621 | D36: Alquiler Angela Sierra 15-16 feb | E36: 475000 | I36: 45623 | J36: Avalúo Abono 50% | K36: 500000
I37: 45623 | J37: Certificado de tradición | K37: 20900
I38: 45625 | J38: Segundo quincena noviembre Jairo | K38: 700000
I39: 45625 | J39: Pago noviembre Omaira López | K39: 400000
I40: 45626 | J40: Gastos bancarios | K40: 47070.66
D41: TOTAL INGRESO | E41: =SUM(E29:E40) -> 4912598 | J41: TOTAL EGRESOS | K41: =SUM(K29:K40) -> 4892520.7 | N41: =+M29-'ESTADO DE RESULTADO'!M22 -> 0
B43: INGRESOS | C43: FECHA | D43: CONCEPTO | E43: ABONO | F43: SALDO | H43: EGRESOS | I43: FECHA | J43: CONCEPTO | K43: VALOR | M43: UTILIDAD
B44: DICIEMBRE | C44: 45635 | D44: Airbnb Johan David Ospina 7 - 8 dic | E44: 812212.67 | H44: DICIEMBRE | I44: 45630 | J44: Avalúo Saldo 50% | K44: 450000 | M44: =+E55-K55 -> -812968.45
C45: 45638 | D45: Alquiler Valentina Tafur 14-15 Dic deposito | E45: 300000 | I45: 45631 | J45: Quimicos piscina | K45: 316515
C46: 45642 | D46: Alquiler Valentina Tafur 14-15 Dic deposito | E46: -300000 | I46: 45639 | J46: Primera quincena diciembre Jairo | K46: 700000
C47: 45649 | D47: Alquiler Diego Quintero 31 - 2 enero | E47: 300000 | I47: 45646 | J47: Internet diciembre | K47: 51500
C48: 45649 | D48: Alquiler Pasadía Museo La Tertulia | E48: 500000 | I48: 45650 | J48: Reparación Guadaña | K48: 350000
C49: 45650 | D49: Alquiler Diego Quintero 31 - 2 enero | E49: 320000 | I49: 45650 | J49: Pipetas de gas 100 y 40 | K49: 338000
C50: 45656 | D50: Airbnb Jhon Posada 26 - 30 dic | E50: 3237492 | I50: 45656 | J50: Liquidación de prestaciones sociales Jairo | K50: 2968000
C51: 45656 | D51: Alquiler Diego Quintero 31 - 2 enero | E51: 800000 | I51: 45656 | J51: Segunda quincena diciembre Jairo | K51: 700000
C52: 45656 | D52: Alquiler Diego Quintero 31 - 2 enero | E52: 130000 | I52: 45656 | J52: Pago diciembre Omaira López | K52: 400000
I53: 45656 | J53: Comisión 26-30 dic Aribnb Jhon Posada | K53: 600000
I54: 45657 | J54: Gastos bancarios | K54: 38658.12
D55: TOTAL INGRESO | E55: =SUM(E44:E54) -> 6099704.7 | J55: TOTAL EGRESOS | K55: =SUM(K44:K54) -> 6912673.1 | N55: =+M44-'ESTADO DE RESULTADO'!N22 -> 0
